releaserr/__init__.py
releaserr/__main__.py
releaserr/cli_utils.py
releaserr/config.py
releaserr/copr.py
releaserr/py.typed
releaserr/scd.py
releaserr/subprocess_util.py
releaserr/toml.py
releaserr/version.py
releaserr/new/__init__.py
releaserr/new/files.py
releaserr/new/sourcehut.py
releaserr/new/data/CONTRIBUTING.md.j2
releaserr/new/data/NEWS.md.j2
releaserr/new/data/NEWS_FRAGMENT.md.j2
releaserr/new/data/README.md.j2
releaserr/new/data/__init__.py
releaserr/new/data/app.spec.j2
releaserr/new/data/blankmod.py.j2
releaserr/new/data/builds-main.yml.j2
releaserr/new/data/builds-mockbuild.yml.j2
releaserr/new/data/copr-Makefile.j2
releaserr/new/data/empty.j2
releaserr/new/data/gitignore.j2
releaserr/new/data/init.py.j2
releaserr/new/data/library.spec.j2
releaserr/new/data/noxfile.py.j2
releaserr/new/data/pyproject.toml.j2
releaserr/new/data/ruff.toml.j2
releaserr/new/data/test-placeholder.py.j2
releaserr-0.1.dev143.dist-info/METADATA
releaserr-0.1.dev143.dist-info/WHEEL
releaserr-0.1.dev143.dist-info/entry_points.txt
releaserr-0.1.dev143.dist-info/licenses/LICENSES/MIT.txt
releaserr-0.1.dev143.dist-info/licenses/LICENSES/Unlicense.txt
releaserr-0.1.dev143.dist-info/RECORD
