Metadata-Version: 2.4
Name: releaserr
Version: 0.1.dev143
Summary: Simple, purpose-built release manager for @gotmax23's projects
Author-email: Maxwell G <maxwell@gtmx.me>
License-Expression: MIT AND Unlicense
License-File: LICENSES/MIT.txt
License-File: LICENSES/Unlicense.txt
Classifier: Development Status :: 3 - Alpha
Classifier: Environment :: Console
Classifier: Programming Language :: Python
Classifier: Programming Language :: Python :: 3.9
Classifier: Programming Language :: Python :: 3.10
Classifier: Programming Language :: Python :: 3.11
Classifier: Programming Language :: Python :: 3.12
Classifier: Programming Language :: Python :: 3.13
Classifier: Typing :: Typed
Requires-Python: >=3.9
Requires-Dist: httpx
Requires-Dist: jinja2
Requires-Dist: pydantic
Requires-Dist: rich
Requires-Dist: sourcehutx>=0.1.0
Requires-Dist: typer>=0.9.0
Requires-Dist: typing-extensions
Provides-Extra: all
Requires-Dist: build; extra == 'all'
Requires-Dist: tomlkit; extra == 'all'
Requires-Dist: twine; extra == 'all'
Provides-Extra: codeqa
Requires-Dist: reuse; extra == 'codeqa'
Requires-Dist: ruff>=0.2.0; extra == 'codeqa'
Provides-Extra: copr
Requires-Dist: copr; extra == 'copr'
Requires-Dist: requests-gssapi; extra == 'copr'
Provides-Extra: dev
Requires-Dist: black; extra == 'dev'
Requires-Dist: build; extra == 'dev'
Requires-Dist: isort; extra == 'dev'
Requires-Dist: mypy; extra == 'dev'
Requires-Dist: nox; extra == 'dev'
Requires-Dist: reuse; extra == 'dev'
Requires-Dist: ruff>=0.2.0; extra == 'dev'
Requires-Dist: tomli-w; extra == 'dev'
Requires-Dist: tomli; (python_version < '3.11') and extra == 'dev'
Requires-Dist: tomlkit; extra == 'dev'
Requires-Dist: twine; extra == 'dev'
Requires-Dist: types-requests; extra == 'dev'
Provides-Extra: formatters
Requires-Dist: black; extra == 'formatters'
Requires-Dist: isort; extra == 'formatters'
Provides-Extra: typing
Requires-Dist: mypy; extra == 'typing'
Requires-Dist: nox; extra == 'typing'
Requires-Dist: tomli-w; extra == 'typing'
Requires-Dist: tomli; (python_version < '3.11') and extra == 'typing'
Requires-Dist: tomlkit; extra == 'typing'
Requires-Dist: types-requests; extra == 'typing'
